model_arena/Regression.py
model_arena/__init__.py
model_arena-0.0.4.dist-info/LICENSE
model_arena-0.0.4.dist-info/METADATA
model_arena-0.0.4.dist-info/WHEEL
model_arena-0.0.4.dist-info/top_level.txt
model_arena-0.0.4.dist-info/RECORD
