Metadata-Version: 2.1
Name: model-arena
Version: 0.0.4
Summary: A model extension package
Home-page: https://github.com/TanselArif-21/LinearRegression
Author: Tansel Arif
Author-email: tanselarif@live.co.uk
License: UNKNOWN
Platform: UNKNOWN
Classifier: Programming Language :: Python :: 3
Classifier: License :: OSI Approved :: MIT License
Classifier: Operating System :: OS Independent
Requires-Dist: numpy
Requires-Dist: pandas
Requires-Dist: sklearn
Requires-Dist: scipy
